LICENSE
README.md
setup.py
learntester/__init__.py
learntester/admin.py
learntester/config.py
learntester/models.py
learntester/tests.py
learntester/urls.py
learntester/views.py
learntester.egg-info/PKG-INFO
learntester.egg-info/SOURCES.txt
learntester.egg-info/dependency_links.txt
learntester.egg-info/not-zip-safe
learntester.egg-info/requires.txt
learntester.egg-info/top_level.txt